nonebot_plugin_pingti-0.2.0.post1.dist-info/METADATA
nonebot_plugin_pingti-0.2.0.post1.dist-info/WHEEL
nonebot_plugin_pingti-0.2.0.post1.dist-info/entry_points.txt
nonebot_plugin_pingti-0.2.0.post1.dist-info/licenses/LICENSE
nonebot_plugin_pingti/__init__.py
nonebot_plugin_pingti/__main__.py
nonebot_plugin_pingti/config.py
nonebot_plugin_pingti/data_source.py
nonebot_plugin_pingti-0.2.0.post1.dist-info/RECORD
