Metadata-Version: 2.1
Name: nonebot-plugin-pingti
Version: 0.2.0.post1
Summary: Shop with lower prices by searching with alternative keywords.
Author-Email: student_2333 <lgc2333@126.com>
License: MIT
Project-URL: homepage, https://github.com/lgc-NB2Dev/nonebot-plugin-pingti
Requires-Python: <4.0,>=3.9
Requires-Dist: nonebot2>=2.4.0
Requires-Dist: nonebot-plugin-alconna>=0.54.1
Requires-Dist: nonebot-plugin-waiter>=0.8.0
Requires-Dist: cookit[loguru,nonebot-alconna,pydantic]>=0.8.4
Requires-Dist: httpx>=0.27.0
